klivi/__init__.py
klivi/__main__.py
klivi/cli.py
klivi/console.py
klivi/constant.py
klivi/lexer.py
klivi/parser.py
klivi/queue.py
klivi/render.py
klivi/stack.py
klivi/view.py
klivi/utils/__init__.py
klivi/utils/array.py
klivi/utils/dictionary.py
klivi/utils/fs.py
klivi/utils/objects.py
klivi/utils/period.py
klivi-0.3.0.dist-info/LICENSE
klivi-0.3.0.dist-info/METADATA
klivi-0.3.0.dist-info/WHEEL
klivi-0.3.0.dist-info/entry_points.txt
klivi-0.3.0.dist-info/top_level.txt
klivi-0.3.0.dist-info/RECORD
