Metadata-Version: 2.1
Name: klivi
Version: 0.3.0
Summary: klivi, build cross platform desktop app with html
Home-page: https://github.com/ardustri/klivi
Author: Ardustri
Author-email: contact@klivi.ardustri.org
License: MPL-2.0
Platform: UNKNOWN
Classifier: Programming Language :: Python :: 3
Requires-Dist: colorama
Requires-Dist: pywebview
Requires-Dist: xmltodict
